{
    "type": "seasong:thalassic_sea",
    "generator": {
        "type": "minecraft:flat",
        "settings": {
            "biome": "seasong:thalassic_ocean",
            "layers": [
                {
                    "block": "minecraft:barrier",
                    "height": 1
                },
                {
                    "block": "minecraft:water",
                    "height": 375
                },
                {
                    "block": "minecraft:barrier",
                    "height": 5
                }
            ],
            "structure_overrides": []
        }
    }
}
